aeripy/__init__.py
aeripy/aeripy_api.py
aeripy/endpoints.py
aeripy/exceptions.py
aeripy/models.py
aeripy/rest_adapter.py
aeripy/util.py
aeripy-0.2.16.dist-info/LICENSE
aeripy-0.2.16.dist-info/METADATA
aeripy-0.2.16.dist-info/WHEEL
aeripy-0.2.16.dist-info/top_level.txt
aeripy-0.2.16.dist-info/RECORD
