Metadata-Version: 2.1
Name: aeripy
Version: 0.2.16
Summary: Aeries API Python Adapter
Home-page: https://aeripy.readthedocs.io/
Author: Ryan Aguilar
Author-email: ryanaguilar323@gmail.com
License: Simplified BSD License
Classifier: Intended Audience :: Developers
Classifier: License :: OSI Approved :: BSD License
Classifier: Programming Language :: Python
Classifier: Programming Language :: Python :: 3
Classifier: Programming Language :: Python :: 3.8
Classifier: Programming Language :: Python :: 3.9
Classifier: Operating System :: OS Independent
License-File: LICENSE
Requires-Dist: requests
